dacy/__init__.py
dacy/about.py
dacy/download.py
dacy/load.py
dacy/utils.py
dacy/datasets/__init__.py
dacy/datasets/constants.py
dacy/datasets/dane.py
dacy/datasets/names.py
dacy/datasets/lookup_tables/README.md
dacy/datasets/lookup_tables/__init__.py
dacy/datasets/lookup_tables/names.csv
dacy/hate_speech/__init__.py
dacy/hate_speech/wrapped_models.py
dacy/ner/__init__.py
dacy/ner/fine_grained.py
dacy/ner/wrapped_models.py
dacy/score/__init__.py
dacy/score/input_length.py
dacy/score/score.py
dacy/sentiment/__init__.py
dacy/sentiment/wrapped_models.py
dacy-2.7.8.dist-info/LICENSE
dacy-2.7.8.dist-info/METADATA
dacy-2.7.8.dist-info/WHEEL
dacy-2.7.8.dist-info/entry_points.txt
dacy-2.7.8.dist-info/top_level.txt
dacy-2.7.8.dist-info/RECORD
