Metadata-Version: 2.1
Name: dacy
Version: 2.7.8
Summary: A Danish pipeline trained in SpaCy that has achieved State-of-the-Art performance on all dependency parsing, NER and POS-tagging for Danish
Author: Lasse Hansen, Emil Jessen
Author-email: Kenneth Enevoldsen <kennethcenevoldsen@gmail.com>
License: Apache License
Project-URL: homepage, https://centre-for-humanities-computing.github.io/DaCy/
Project-URL: documentation, https://centre-for-humanities-computing.github.io/DaCy/
Project-URL: repository, https://github.com/centre-for-humanities-computing/DaCy
Keywords: nlp,danish,spacy-universe
Classifier: Development Status :: 5 - Production/Stable
Classifier: Environment :: Console
Classifier: Intended Audience :: Developers
Classifier: Intended Audience :: Science/Research
Classifier: Topic :: Scientific/Engineering
Classifier: Topic :: Scientific/Engineering :: Artificial Intelligence
Classifier: Operating System :: POSIX :: Linux
Classifier: Operating System :: MacOS :: MacOS X
Classifier: Operating System :: Microsoft :: Windows
Classifier: Programming Language :: Python :: 3
Classifier: Programming Language :: Python :: 3.9
Classifier: Programming Language :: Python :: 3.10
Classifier: Programming Language :: Python :: 3.11
Classifier: Programming Language :: Python :: 3.12
Requires-Python: >=3.9
License-File: LICENSE
Requires-Dist: spacy-wrap>=1.4.1
Requires-Dist: spacy-experimental>=0.6.2
Requires-Dist: spacy[transformers]>=3.2.0
Requires-Dist: pandas>=1.0.0
Requires-Dist: tqdm>=4.42.1
Provides-Extra: dev
Requires-Dist: cruft>=2.0.0; extra == "dev"
Requires-Dist: pyright>=1.1.339; extra == "dev"
Requires-Dist: ruff>=0.0.270; extra == "dev"
Provides-Extra: docs
Requires-Dist: sphinx==5.3.0; extra == "docs"
Requires-Dist: furo>=2022.12.7; extra == "docs"
Requires-Dist: sphinx-copybutton>=0.5.1; extra == "docs"
Requires-Dist: sphinxext-opengraph>=0.7.3; extra == "docs"
Requires-Dist: sphinx-design>=0.3.0; extra == "docs"
Requires-Dist: sphinx-togglebutton>=0.2.3; extra == "docs"
Requires-Dist: myst-nb>=0.6.0; extra == "docs"
Requires-Dist: sphinxcontrib-bibtex>=2.0.0; extra == "docs"
Requires-Dist: docutils==0.17.1; extra == "docs"
Requires-Dist: jupyter>=1.0.0; extra == "docs"
Requires-Dist: wikidata>=0.7.0; extra == "docs"
Requires-Dist: asent>=0.4.2; extra == "docs"
Requires-Dist: augmenty>=1.0.2; extra == "docs"
Requires-Dist: textdescriptives>=2.1.0; extra == "docs"
Requires-Dist: seaborn>=0.11.2; extra == "docs"
Requires-Dist: altair>=4.1.0; extra == "docs"
Requires-Dist: datasets>=1.14.0; extra == "docs"
Provides-Extra: tests
Requires-Dist: pytest>=7.1.2; extra == "tests"
Requires-Dist: pytest-cov>=3.0.0; extra == "tests"
Requires-Dist: pytest-instafail>=0.4.2; extra == "tests"
